docdetect/__init__.py
docdetect/canny_edges.py
docdetect/hough_lines.py
docdetect/intersections.py
docdetect/line_utils.py
docdetect/processor.py
docdetect/quadrilaterals.py
docdetect1-1.0.1.dist-info/LICENSE
docdetect1-1.0.1.dist-info/METADATA
docdetect1-1.0.1.dist-info/WHEEL
docdetect1-1.0.1.dist-info/top_level.txt
docdetect1-1.0.1.dist-info/zip-safe
docdetect1-1.0.1.dist-info/RECORD
