Metadata-Version: 2.1
Name: docdetect1
Version: 1.0.1
Summary: Real-time detection of documents in images.
Home-page: https://github.com/haocse/docdetect-1
Author: haotran
Author-email: hao.cse@gmail.com
License: MIT
Keywords: docdetect document-detection rectangle-detection edge-detection
Platform: UNKNOWN
Classifier: Development Status :: 3 - Alpha
Classifier: Intended Audience :: Developers
Classifier: License :: OSI Approved :: MIT License
Classifier: Natural Language :: English
Classifier: Programming Language :: Python :: 2.7
Classifier: Programming Language :: Python :: 3.6
Classifier: Topic :: Scientific/Engineering :: Image Recognition
Classifier: Topic :: Software Development :: Libraries :: Python Modules
Classifier: Topic :: Utilities
Requires-Dist: numpy
Requires-Dist: opencv-python
